combinação_fotos/__init__.py
combinação_fotos/file1_name.py
combinação_fotos/file2_name.py
combinação_fotos/main.py
combina_o_fotos-0.0.1.dist-info/METADATA
combina_o_fotos-0.0.1.dist-info/WHEEL
combina_o_fotos-0.0.1.dist-info/top_level.txt
combina_o_fotos-0.0.1.dist-info/RECORD
