Metadata-Version: 2.1
Name: combina-o_fotos
Version: 0.0.1
Summary: A criação de pacotes em Python permite combinar duas imagens, utilizando uma delas como base para a paisagem e a outra para as cores, gerando uma nova imagem que mescla elementos de ambas, resultando em uma composição única e criativa.
Home-page: 
Author: Nanda
Author-email: fernandacrosa57@gmail.com
Classifier: Programming Language :: Python :: 3
Classifier: License :: OSI Approved :: MIT License
Classifier: Operating System :: OS Independent
Requires-Python: >=3.8
